{
    "last_update_utc": "2025-12-24T09:12:35.823946Z",
    "spot": 157.88,
    "data": [
        {
            "date": "2026-01-16",
            "mstr_pain": 19.0,
            "btc_pain": 88000.0,
            "is_monthly": true
        },
        {
            "date": "2026-02-20",
            "mstr_pain": 480.0,
            "btc_pain": 90000.0,
            "is_monthly": true
        },
        {
            "date": "2026-03-20",
            "mstr_pain": 510.0,
            "btc_pain": 100000.0,
            "is_monthly": true
        }
    ]
}